sparselinear/__init__.py
sparselinear/activationsparsity.py
sparselinear/sparselinear.py
sparselinear-0.0.5.dist-info/LICENSE
sparselinear-0.0.5.dist-info/METADATA
sparselinear-0.0.5.dist-info/WHEEL
sparselinear-0.0.5.dist-info/top_level.txt
sparselinear-0.0.5.dist-info/RECORD
