Metadata-Version: 2.1
Name: sparselinear
Version: 0.0.5
Summary: Pytorch extension library for creating sparse linear layers
Home-page: https://github.com/rain-neuromorphics/SparseLinear
Author: Rain Neuromorphics
Author-email: ross@rain-neuromorphics.com
License: MIT
Keywords: pytorch,sparse,linear
Platform: UNKNOWN
Requires-Python: >=3.6
Requires-Dist: numpy
Requires-Dist: torch
